opencensus/__init__.py
opencensus/ext/__init__.py
opencensus/ext/zipkin/__init__.py
opencensus/ext/zipkin/trace_exporter/__init__.py
opencensus_ext_zipkin-0.2.0.dist-info/METADATA
opencensus_ext_zipkin-0.2.0.dist-info/WHEEL
opencensus_ext_zipkin-0.2.0.dist-info/namespace_packages.txt
opencensus_ext_zipkin-0.2.0.dist-info/top_level.txt
opencensus_ext_zipkin-0.2.0.dist-info/RECORD
