Metadata-Version: 2.1
Name: opencensus-ext-zipkin
Version: 0.2.0
Summary: OpenCensus Zipkin Trace Exporter
Home-page: https://github.com/census-instrumentation/opencensus-python/tree/master/contrib/opencensus-ext-zipkin
Author: OpenCensus Authors
Author-email: census-developers@googlegroups.com
License: Apache-2.0
Platform: UNKNOWN
Classifier: Intended Audience :: Developers
Classifier: Development Status :: 3 - Alpha
Classifier: Intended Audience :: Developers
Classifier: License :: OSI Approved :: Apache Software License
Classifier: Programming Language :: Python
Classifier: Programming Language :: Python :: 2
Classifier: Programming Language :: Python :: 2.7
Classifier: Programming Language :: Python :: 3
Classifier: Programming Language :: Python :: 3.4
Classifier: Programming Language :: Python :: 3.5
Classifier: Programming Language :: Python :: 3.6
Classifier: Programming Language :: Python :: 3.7
Requires-Dist: opencensus (<1.0.0,>=0.4.0)
